flake8_class_attributes_order/__init__.py
flake8_class_attributes_order/checker.py
flake8_class_attributes_order/model_parts_info.py
flake8_class_attributes_order/node_type_weights.py
flake8_class_attributes_order/ordering_errors.py
flake8_class_attributes_order-0.3.0.dist-info/LICENSE
flake8_class_attributes_order-0.3.0.dist-info/METADATA
flake8_class_attributes_order-0.3.0.dist-info/WHEEL
flake8_class_attributes_order-0.3.0.dist-info/entry_points.txt
flake8_class_attributes_order-0.3.0.dist-info/top_level.txt
flake8_class_attributes_order-0.3.0.dist-info/RECORD
